Workbook

Sheet README
A1: S&P 500 Sustainability Framework — Data Source Register
A2: Built 2026-09-12. Merged pillar taxonomy: original ESG reading + corporate-resilience reading (10-K hitwords).
A4: MERGED PILLAR TAXONOMY
A5: The two framings in the plan doc were not the same three pillars. They are merged here as follows:
A7: P1 Environmental & Resource Efficiency
A8: = original 'Environmental' + corporate 'Resource & Operational Efficiency'.
A9: Physical footprint AND how efficiently inputs are converted to output. Both are backward-looking, measured.
A11: P2 Transition & Structural Risk
A12: = original 'Transition' + corporate 'Structural / Disruption Risk'.
A13: Forward-looking exposure. Carbon price is one shock among several (tariffs, obsolescence, concentration).
A15: P3 Governance & Capital Stewardship
A16: = original 'Governance' + corporate 'Governance & Capital Stewardship'.
... A52: Orange rows = Tier 3, structurally narrow (heavy industry only)

Sheet Data Sources
A1: ID | B1: Source | C1: Owner | D1: What it is | E1: What you get from it | F1: Pillar | G1: 2nd pillar | H1: Feeds indicators | I1: Est. coverage (of 500) | J1: Coverage % | K1: Tier | L1: Confidence | M1: Access method | N1: Python / package | O1: Endpoint or download URL | P1: Auth | Q1: Format | R1: Gotchas & rate limits | S1: Effort | T1: Priority
A2: S01 | B2: SEC EDGAR — XBRL company facts | C2: SEC | D2: Structured financial-statement data tagged in every filing. | E2: Revenue, EBIT, EBITDA inputs, FCF components, capex, R&D, buybacks, dividends, total assets. | F2: P1/P2/P3 | G2: — | H2: Carbon intensity denominator; carbon-price exposure; affordability; capital stewardship | I2: 500 | J2: =IFERROR(I2/500,"") -> 1 | K2: 1 - Universal | L2: Verified (structural) | M2: REST JSON API | N2: requests, pandas, edgartools | O2: https://data.sec.gov/api/xbrl/companyfacts/CIK##########.json | P2: None (UA required) | Q2: JSON | R2: User-Agent MUST contain a real contact address or you are blocked. Max 10 req/s. Revenue splits across 4+ tags — write the fallback chain (RevenueFromContractWithCustomerExcludingAssessedTax, Revenues, SalesRevenueNet, RevenueFromContractWithCustomerIncludingAssessedTax). | S2: Low | T2: MUST
A3: S02 | B3: SEC EDGAR — 10-K full text | C3: SEC | D3: The annual report itself. Item 1A risk factors, Item 7 MD&A. | E3: Risk-factor language, climate/transition discussion, green capex mentions, segment narrative, hitword counts. | F3: P1/P2 | G3: P3 | H3: Green revenue share; clean capex; structural risk hitwords; emissions targets | I3: 500 | J3: =IFERROR(I3/500,"") -> 1 | K3: 1 - Universal | L3: Verified (structural) | M3: Bulk download + parse | N3: sec-edgar-downloader, edgartools, BeautifulSoup | O3: https://www.sec.gov/cgi-bin/browse-edgar / https://data.sec.gov/submissions/CIK##########.json | P3: None (UA required) | Q3: HTML / iXBRL | R3: 75k-200k tokens per filing — DO NOT send whole filings to an agent. Strip HTML, locate the section by heading, keep +/-2-3k chars around keyword hits, send 5-15k tokens. ~15x cheaper and more accurate. Cache every filing on first fetch. | S3: Med | T3: MUST
A4: S03 | B4: SEC EDGAR full-text search | C4: SEC | D4: Keyword search across all filings without downloading them. | E4: Hit counts and filing locations for any phrase, filterable by form type and date. | F4: P2 | G4: P3 | H4: Structural risk hitwords; climate language prevalence | I4: 500 | J4: =IFERROR(I4/500,"") -> 1 | K4: 1 - Universal | L4: Verified (structural) | M4: Undocumented JSON endpoint | N4: requests | O4: https://efts.sec.gov/LATEST/search-index?q=%22phrase%22&forms=10-K (JSON behind sec.gov/edgar/search) | P4: None (UA required) | Q4: JSON | R4: Undocumented — confirm the endpoint shape by opening sec.gov/edgar/search in devtools before relying on it. Only covers 2001+. Gives hit counts, not context: you still need S02 for the surrounding sentence. | S4: Low | T4: SHOULD
A5: S04 | B5: SEC EDGAR — DEF 14A proxy statements | C5: SEC | D5: Annual proxy. Governance and compensation disclosure. | E5: Board independence, committee structure, climate-oversight committee, ESG-linked pay, PSU/clawback terms, say-on-pay. | F5: P3 | G5: — | H5: Climate governance booleans; comp alignment; board independence | I5: 498 | J5: =IFERROR(I5/500,"") -> 0.996 | K5: 1 - Universal | L5: Estimated | M5: Bulk download + parse | N5: sec-edgar-downloader, edgartools | O5: Same as S02, form type DEF 14A | P5: None (UA required) | Q5: HTML | R5: Prose-heavy and inconsistently structured. Extract BOOLEANS with verbatim quotes, not graded scores — graded scores over prose is where hallucination lives. This is your only near-complete pillar, so it deserves the best extraction. | S5: Med | T5: MUST
A6: S05 | B6: SEC Exhibit 21 — subsidiary lists | C6: SEC | D6: Company's own declared list of subsidiaries, filed with the 10-K. | E6: Subsidiary legal names + jurisdiction, per parent. Ground truth for rolling facility data up to the listed entity. | F6: X | G6: P1 | H6: Entity resolution (prerequisite for every facility-based source) | I6: 490 | J6: =IFERROR(I6/500,"") -> 0.98 | K6: 1 - Universal | L6: Estimated | M6: Parse from 10-K exhibits | N6: sec-edgar-downloader, rapidfuzz | O6: Filed as EX-21 alongside the 10-K (see S02) | P6: None (UA required) | Q6: HTML / text | R6: Companies may omit subsidiaries deemed immaterial, so a short list does NOT mean a simple company. Format is wildly inconsistent (tables, lists, paragraphs). No ownership percentages — get those from S15. | S6: Med | T6: MUST
A7: S06 | B7: GLEIF — LEI Level 1 & 2 | C7: GLEIF | D7: Global legal entity identifier registry with declared parent relationships. | E7: Legal entity names, addresses, direct parent and ultimate parent LEIs. Machine-readable corporate structure. | F7: X | G7: — | H7: Entity resolution (second opinion on Exhibit 21) | I7: 500 | J7: =IFERROR(I7/500,"") -> 1 | K7: 1 - Universal | L7: Estimated | M7: REST API + bulk file | N7: requests, pandas | O7: https://api.gleif.org/api/v1/lei-records | P7: None | Q7: JSON / CSV | R7: Level 2 parent data is self-declared and companies can claim exemptions, so child-to-parent links are patchier than the entity records themselves. Use ALONGSIDE Exhibit 21, not instead of it. | S7: Low | T7: SHOULD
A8: S07 | B8: Market data (prices, market cap) | C8: Yahoo / other | D8: Price and share-count feed for the constituent list. | E8: Market cap (bubble size on the 3D map), sector/industry labels, price history for the portfolio work. | F8: X | G8: P2 | H8: Visual encoding; bonus-question portfolio construction | I8: 500 | J8: =IFERROR(I8/500,"") -> 1 | K8: 1 - Universal | L8: Estimated | M8: Python library | N8: yfinance | O8: https://pypi.org/project/yfinance/ | P8: None | Q8: DataFrame | R8: Unofficial and rate-limited; it breaks periodically. Cache to disk on first pull. The sustainability/ESG field is thin and vendor-sourced — fine as a fallback controversy flag, NOT as a primary indicator. | S8: Low | T8: MUST
A9: S08 | B9: S&P 500 constituent list | C9: Wikipedia / datahub | D9: The index membership itself, with tickers, CIK and GICS sector. | E9: Ticker, company name, CIK (the join key to everything SEC), GICS sector and sub-industry. | F9: P1/P2/P3 | G9: — | H9: Universe definition; sector normalisation buckets | I9: 500 | J9: =IFERROR(I9/500,"") -> 1 | K9: 1 - Universal | L9: Verified (structural) | M9: HTML table scrape | N9: pandas.read_html | O9: https://en.wikipedia.org/wiki/List_of_S%26P_500_companies | P9: None | Q9: HTML table | R9: Includes CIK directly, which saves a lookup step. Freeze the list at one date and commit it to the repo — membership changes mid-build will silently break joins. Note ~503 tickers for 500 companies (dual share classes). | S9: Low | T9: MUST
A10: S09 | B10: SBTi target list | C10: Science Based Targets initiative | D10: Public register of validated emission-reduction targets. | E10: Target type (near-term / net-zero), target year, baseline year, ambition, validation date, sector. | F10: P2 | G10: P3 | H10: Regulatory momentum; affordability numerator; target credibility | I10: 275 | J10: =IFERROR(I10/500,"") -> 0.55 | K10: 2 - Broad | L10: Verified (2022 figure) | M10: CSV download | N10: pandas | O10: https://sciencebasedtargets.org/companies-taking-action | P10: None | Q10: CSV / XLSX | R10: Name matching to tickers is the only real work — match on normalised legal name within country. Gives you the target YEAR and AMBITION, which are the two inputs to the affordability calculation. Companies with no SBTi target still need a counterfactual target, not a null. | S10: Low | T10: MUST
A11: S10 | B11: Corporate sustainability reports | C11: Companies / responsibilityreports.com | D11: The self-published PDF. Aggregator indexes them by ticker. | E11: Scope 1/2/3, renewable %, water, waste, targets, assurance statements. Everything not in the 10-K. | F11: P1 | G11: P2 | H11: Scope 3; energy mix; water/waste; stated targets | I11: 400 | J11: =IFERROR(I11/500,"") -> 0.8 | K11: 2 - Broad | L11: Estimated | M11: Scrape aggregator, then fetch PDFs | N11: requests, pdfplumber, PyMuPDF | O11: https://www.responsibilityreports.com | P11: None | Q11: PDF | R11: The hard part is finding 500 URLs, not reading them — the aggregator solves exactly that. PDFs are 60-150pp; pre-filter to the data-table pages before extraction. Self-reported: treat every number as a CLAIM with a quote attached, never as a fact. | S11: High | T11: SHOULD
A12: S11 | B12: Violation Tracker | C12: Good Jobs First | D12: Aggregated US enforcement actions across ~500 federal and state agencies. | E12: Penalties by company and parent: environmental, safety, labor, consumer, financial. Already mapped to parent company. | F12: P3 | G12: P1 | H12: Controversy flag (built from records, not news sentiment) | I12: 400 | J12: =IFERROR(I12/500,"") -> 0.8 | K12: 2 - Broad | L12: Estimated | M12: Web UI; bulk on request | N12: requests, BeautifulSoup | O12: https://violationtracker.goodjobsfirst.org | P12: Free account for some features | Q12: HTML / CSV export | R12: NO public API — this is the friction. Broader than you expect (financial + labor + consumer, not just environmental), so it is your highest-coverage controversy source. Its parent mapping is also a free second opinion on your entity resolution. Check licence terms before redistributing. | S12: Med | T12: SHOULD
A13: S12 | B13: Senate LDA lobbying disclosures | C13: US Senate | D13: Mandatory quarterly lobbying registration and spend reports. | E13: Registrant, client, spend, and specific issues/bills lobbied on. Climate-relevant filings are extractable. | F13: P2 | G13: P3 | H13: Say-do gap: pledges vs. political spending | I13: 350 | J13: =IFERROR(I13/500,"") -> 0.7 | K13: 2 - Broad | L13: Estimated | M13: REST API + bulk XML | N13: requests, pandas | O13: https://lda.senate.gov/api/ | P13: Free API key | Q13: JSON / XML | R13: This is the purest say-do signal available for free: net-zero pledge next to membership in a trade group litigating against emissions rules. Attribution to parent is messy (firms lobby via associations). High payoff, medium reliability — treat as a flag, not a score. | S13: Med | T13: STRETCH
... A30: S29 | B30: Stanford Securities Class Action Clearinghouse | C30: Stanford Law | D30: Register of US federal securities class actions since 1996. | E30: Filing date, defendant, allegations, status, settlement amount. | F30: P3 | G30: — | H30: Controversy flag (governance / disclosure integrity) | I30: 150 | J30: =IFERROR(I30/500,"") -> 0.3 | K30: 3 - Narrow | L30: Estimated | M30: Web scrape | N30: requests, BeautifulSoup | O30: https://securities.stanford.edu | P30: None | Q30: HTML | R30: Specifically disclosure-integrity litigation, which is more relevant to a framework built on verifying disclosure than generic controversy counts. No API; scrape the index pages. Skewed toward large caps (more litigation targets), so normalise or use as a binary. | S30: Low | T30: STRETCH

Sheet Pillar Mapping
A1: Pillar | B1: Origin | C1: Indicator | D1: What it measures | E1: How it is computed | F1: Primary source | G1: Fallback source | H1: Est. coverage | I1: Notes / risk
A2: P1 Environmental & Resource Efficiency | B2: Original ESG | C2: Carbon intensity | D2: Scope 1+2 emissions per $m revenue. | E2: (GHGRP measured Scope 1 + location-based Scope 2 via eGRID) / XBRL revenue. Percentile within GICS sector. | F2: S15, S19, S01 | G2: S10 self-reported | H2: 500 | I2: Measured for ~69, self-reported for ~455, imputed for the rest. Carry the SOURCE TIER per company: EPA-measured / quote-verified disclosure / modelled. That three-tier verifiability axis is the differentiator.
A3: P1 Environmental & Resource Efficiency | B3: Original ESG | C3: Energy mix | D3: Share of electricity from low-carbon sources. | E3: Utilities: EIA 923 generation by fuel. Others: Green Power Partnership kWh / total, else sector median. | F3: S20, S21 | G3: S10 self-reported | H3: 500 | I3: Cross-check against eGRID regional mix. A renewable claim that does not move location-based Scope 2 is an unbundled REC purchase — flag it, do not credit it.
A4: P1 Environmental & Resource Efficiency | B4: Original ESG | C4: Resource & waste intensity | D4: Non-carbon environmental burden, weighted by harm. | E4: RSEI score (toxicity x population weighted) per $m revenue. Water volume x Aqueduct stress where available. | F4: S17, S16, S26 | G4: Sector median | H4: 120 | I4: Manufacturing and mining only. This indicator is EMPTY for over half the index — let SASB materiality weighting handle that rather than imputing.
A5: P1 Environmental & Resource Efficiency | B5: Corporate (10-K) | C5: Input & operational efficiency | D5: How efficiently inputs convert to output; exposure to input cost shocks. | E5: COGS / revenue, and energy cost intensity, from XBRL. Hitword density for input-cost and supply-chain risk in Item 1A. | F5: S01, S02 | G5: — | H5: 500 | I5: This is the bridge between the two framings: resource efficiency is both an environmental and a margin story. Raw hitword counts measure document length — use the text-vs-XBRL DISCREPANCY, not the count.
A6: P2 Transition & Structural Risk | B6: Original ESG | C6: Carbon-price exposure | D6: Margin damage from a shadow carbon price. | E6: (Scope 1+2 x assumed $/tonne) / EBITDA. Price is a user-facing slider, default $100, bonus scenario $150. | F6: S15, S01 | G6: S10 self-reported | H6: 500 | I6: Transparent arithmetic, no black box. Feeds the bonus question directly: reported EBIT vs. carbon-adjusted EBIT, distance from the diagonal = unpriced liability.
A7: P2 Transition & Structural Risk | B7: New (finance view) | C7: Transition affordability | D7: Whether the company can pay for the transition it has promised. | E7: ((current emissions - target emissions) x sector abatement cost/tonne / years to target) / free cash flow. | F7: S09, S15, S01 | G7: Counterfactual target | H7: 500 | I7: YOUR STRONGEST INDICATOR AND YOUR RISKIEST. Multiplies three uncertain quantities, so error compounds. Hand-check the 10 most extreme values before showing anyone. No stated target = score against the sector median commitment, marked as imputed, confidence penalised.
A8: P2 Transition & Structural Risk | B8: Original ESG | C8: Innovation & regulatory momentum | D8: Whether capability and commitment are actually being built. | E8: Y02 patent share of recent filings + trend. SBTi validated (binary). R&D intensity from XBRL. | F8: S24, S09, S01 | G8: — | H8: 500 | I8: Y02 is the differentiator nobody else will have. True zero for financials and services — report as zero-with-explanation, not null. Combine with GEM construction pipeline for heavy industry.
A9: P2 Transition & Structural Risk | B9: Corporate (10-K) | C9: Structural / disruption exposure | D9: Non-climate shocks that could end the business. | E9: Item 1A hitword clusters weighted by POSITION in the section and proximity to intensifiers ('material adverse effect'). | F9: S02, S03 | G9: — | H9: 500 | I9: Position beats frequency — every company mentions litigation, but what comes FIRST in Item 1A is what management fears. Naive counting has no negation handling; name that limitation in the pitch rather than hiding it.
A10: P3 Governance & Capital Stewardship | B10: Original ESG | C10: Climate governance | D10: Whether climate is actually governed, not just discussed. | E10: Four booleans from DEF 14A: climate-oversight committee / comp tied to emissions target / third-party assurance / boundary stated. | F10: S04 | G10: S10 | H10: 498 | I10: Booleans with verbatim quotes are robust. Graded scores over prose are where hallucination lives. This is your most complete indicator — make it the backbone of the full-500 view.
A11: P3 Governance & Capital Stewardship | B11: Corporate (proxy) | C11: Compensation alignment | D11: Whether pay is tied to long-term outcomes. | E11: Presence of PSUs, multi-year performance periods, clawback provisions, ESG-linked metrics. Keyword + quote. | F11: S04 | G11: — | H11: 498 | I11: Same extraction pipeline as climate governance, so near-zero marginal cost. Watch negation: 'we do not maintain a clawback policy' contains the keyword and means the opposite.
A12: P3 Governance & Capital Stewardship | B12: Corporate (proxy) | C12: Board independence & structure | D12: Board composition and refreshment. | E12: Independent director count / board size, lead independent director presence, related-party transactions. | F12: S04 | G12: — | H12: 498 | I12: Easy and near-complete, but WEAKLY RELATED TO SUSTAINABILITY. Keep the weight low or a judge will ask why corporate governance boilerplate sits in a climate framework.
A13: P3 Governance & Capital Stewardship | B13: Corporate (10-K + XBRL) | C13: Capital stewardship | D13: Where the money actually goes. | E13: (Capex + R&D) vs. (buybacks + dividends), from XBRL. Compare against management's forward-looking language. | F13: S01, S02 | G13: — | H13: 500 | I13: The purest say-do test available and it needs no PDF extraction: management talks about innovation, XBRL shows what they spent. Ship the discrepancy, not the level.
... A16: X Cross-cutting | B16: Prerequisite | C16: Data confidence score | D16: How much evidence sits behind each company's score. | E16: Share of indicators quote-verified vs. imputed, weighted by pillar. Rendered as OPACITY on the 3D map. | F16: Manifest | G16: — | H16: 500 | I16: This is the disclosure penalty made visible: a company floating in the good corner but nearly transparent is claiming to be good without evidence. Costs no axis, uses a free visual channel, and is the best one-second explanation of your whole framework.

Sheet Coverage Summary
A1: Coverage Summary
A2: All counts are formulas over the Data Sources sheet — edit a coverage number there and these update.
A4: By coverage tier
A5: Tier | B5: # sources | C5: Mean coverage (companies) | D5: Mean %
A6: 1 - Universal | B6: =COUNTIF('Data Sources'!$K$2:$K$30,$A6) -> 8 | C6: =IFERROR(ROUND(SUMIF('Data Sources'!$K$2:$K$30,$A6,'Data Sources'!$I$2:$I$30)/COUNTIF('Data Sources'!$K$2:$K$30,$A6),0),0) -> 499 | D6: =IFERROR(C6/500,"") -> 0.998
A7: 2 - Broad | B7: =COUNTIF('Data Sources'!$K$2:$K$30,$A7) -> 6 | C7: =IFERROR(ROUND(SUMIF('Data Sources'!$K$2:$K$30,$A7,'Data Sources'!$I$2:$I$30)/COUNTIF('Data Sources'!$K$2:$K$30,$A7),0),0) -> 379 | D7: =IFERROR(C7/500,"") -> 0.758
A8: 3 - Narrow | B8: =COUNTIF('Data Sources'!$K$2:$K$30,$A8) -> 15 | C8: =IFERROR(ROUND(SUMIF('Data Sources'!$K$2:$K$30,$A8,'Data Sources'!$I$2:$I$30)/COUNTIF('Data Sources'!$K$2:$K$30,$A8),0),0) -> 127 | D8: =IFERROR(C8/500,"") -> 0.254
A11: By build priority
A12: Priority | B12: # sources | C12: Mean coverage (companies) | D12: Mean %
A13: MUST | B13: =COUNTIF('Data Sources'!$T$2:$T$30,$A13) -> 8 | C13: =IFERROR(ROUND(SUMIF('Data Sources'!$T$2:$T$30,$A13,'Data Sources'!$I$2:$I$30)/COUNTIF('Data Sources'!$T$2:$T$30,$A13),0),0) -> 417 | D13: =IFERROR(C13/500,"") -> 0.834
A14: SHOULD | B14: =COUNTIF('Data Sources'!$T$2:$T$30,$A14) -> 10 | C14: =IFERROR(ROUND(SUMIF('Data Sources'!$T$2:$T$30,$A14,'Data Sources'!$I$2:$I$30)/COUNTIF('Data Sources'!$T$2:$T$30,$A14),0),0) -> 260 | D14: =IFERROR(C14/500,"") -> 0.52
A15: STRETCH | B15: =COUNTIF('Data Sources'!$T$2:$T$30,$A15) -> 10 | C15: =IFERROR(ROUND(SUMIF('Data Sources'!$T$2:$T$30,$A15,'Data Sources'!$I$2:$I$30)/COUNTIF('Data Sources'!$T$2:$T$30,$A15),0),0) -> 178 | D15: =IFERROR(C15/500,"") -> 0.356
A16: VALIDATION | B16: =COUNTIF('Data Sources'!$T$2:$T$30,$A16) -> 1 | C16: =IFERROR(ROUND(SUMIF('Data Sources'!$T$2:$T$30,$A16,'Data Sources'!$I$2:$I$30)/COUNTIF('Data Sources'!$T$2:$T$30,$A16),0),0) -> 450 | D16: =IFERROR(C16/500,"") -> 0.9
A19: By primary pillar
A20: Primary pillar | B20: # sources | C20: Mean coverage (companies) | D20: Mean %
A21: P1 | B21: =COUNTIF('Data Sources'!$F$2:$F$30,$A21) -> 10 | C21: =IFERROR(ROUND(SUMIF('Data Sources'!$F$2:$F$30,$A21,'Data Sources'!$I$2:$I$30)/COUNTIF('Data Sources'!$F$2:$F$30,$A21),0),0) -> 161 | D21: =IFERROR(C21/500,"") -> 0.322
A22: P2 | B22: =COUNTIF('Data Sources'!$F$2:$F$30,$A22) -> 7 | C22: =IFERROR(ROUND(SUMIF('Data Sources'!$F$2:$F$30,$A22,'Data Sources'!$I$2:$I$30)/COUNTIF('Data Sources'!$F$2:$F$30,$A22),0),0) -> 231 | D22: =IFERROR(C22/500,"") -> 0.462
A23: P3 | B23: =COUNTIF('Data Sources'!$F$2:$F$30,$A23) -> 5 | C23: =IFERROR(ROUND(SUMIF('Data Sources'!$F$2:$F$30,$A23,'Data Sources'!$I$2:$I$30)/COUNTIF('Data Sources'!$F$2:$F$30,$A23),0),0) -> 300 | D23: =IFERROR(C23/500,"") -> 0.6
A24: X | B24: =COUNTIF('Data Sources'!$F$2:$F$30,$A24) -> 4 | C24: =IFERROR(ROUND(SUMIF('Data Sources'!$F$2:$F$30,$A24,'Data Sources'!$I$2:$I$30)/COUNTIF('Data Sources'!$F$2:$F$30,$A24),0),0) -> 485 | D24: =IFERROR(C24/500,"") -> 0.97
A25: P1/P2 | B25: =COUNTIF('Data Sources'!$F$2:$F$30,$A25) -> 1 | C25: =IFERROR(ROUND(SUMIF('Data Sources'!$F$2:$F$30,$A25,'Data Sources'!$I$2:$I$30)/COUNTIF('Data Sources'!$F$2:$F$30,$A25),0),0) -> 500 | D25: =IFERROR(C25/500,"") -> 1
A26: P1/P2/P3 | B26: =COUNTIF('Data Sources'!$F$2:$F$30,$A26) -> 2 | C26: =IFERROR(ROUND(SUMIF('Data Sources'!$F$2:$F$30,$A26,'Data Sources'!$I$2:$I$30)/COUNTIF('Data Sources'!$F$2:$F$30,$A26),0),0) -> 500 | D26: =IFERROR(C26/500,"") -> 1
A29: By build effort
A30: Effort | B30: # sources | C30: Mean coverage (companies) | D30: Mean %
A31: Low | B31: =COUNTIF('Data Sources'!$S$2:$S$30,$A31) -> 13 | C31: =IFERROR(ROUND(SUMIF('Data Sources'!$S$2:$S$30,$A31,'Data Sources'!$I$2:$I$30)/COUNTIF('Data Sources'!$S$2:$S$30,$A31),0),0) -> 342 | D31: =IFERROR(C31/500,"") -> 0.684
A32: Med | B32: =COUNTIF('Data Sources'!$S$2:$S$30,$A32) -> 13 | C32: =IFERROR(ROUND(SUMIF('Data Sources'!$S$2:$S$30,$A32,'Data Sources'!$I$2:$I$30)/COUNTIF('Data Sources'!$S$2:$S$30,$A32),0),0) -> 236 | D32: =IFERROR(C32/500,"") -> 0.472
A33: High | B33: =COUNTIF('Data Sources'!$S$2:$S$30,$A33) -> 3 | C33: =IFERROR(ROUND(SUMIF('Data Sources'!$S$2:$S$30,$A33,'Data Sources'!$I$2:$I$30)/COUNTIF('Data Sources'!$S$2:$S$30,$A33),0),0) -> 217 | D33: =IFERROR(C33/500,"") -> 0.434
A36: Headline numbers
A37: Total sources registered | B37: =COUNTA('Data Sources'!$A$2:$A$30) -> 29
A38: Sources needing no auth at all | B38: =COUNTIF('Data Sources'!$P$2:$P$30,"None*") -> 22
A39: Sources with near-universal coverage (>=450) | B39: =COUNTIF('Data Sources'!$I$2:$I$30,">=450") -> 9
A40: Sources covering under 150 companies | B40: =COUNTIF('Data Sources'!$I$2:$I$30,"<150") -> 8
A41: MUST-build sources | B41: =COUNTIF('Data Sources'!$T$2:$T$30,"MUST") -> 8
A42: Coverage estimates still unverified | B42: =COUNTIF('Data Sources'!$L$2:$L$30,"Estimated") -> 23
A44: Note: 'mean coverage' averages the estimated coverage of the sources in each group. It is a planning heuristic, not a company count — sources overlap.

Sheet Access Cheatsheet
A1: Access Cheatsheet
A2: Install list, auth, rate limits and the snippets worth having before hour zero.
A4: Topic | B4: Detail | C4: Why it matters / what breaks without it
A5: Install (hour 1) | B5: pip install pandas requests openpyxl pyxlsb sec-edgar-downloader edgartools yfinance rapidfuzz pdfplumber beautifulsoup4 lxml | C5: pyxlsb is the one people forget — the EPA parent-company file is XLSB and nothing else reads it.
A6: Install (only if used) | B6: pip install geopandas shapely kagglehub PyMuPDF | C6: geopandas is a heavy install. Only needed for the Aqueduct / FEMA spatial joins. Do not put it on the critical path.
A7: SEC User-Agent | B7: headers = {'User-Agent': 'TeamName yourname@email.com'} | C7: Without a real contact address EDGAR blocks you, usually after you have already written the loop. Set it once in a shared session object.
A8: SEC rate limit | B8: Max 10 requests/second. Sleep 0.11s between calls, or use a token bucket. | C8: Exceeding it gets the IP blocked for a period. With 500 companies x several filings you will hit this immediately.
A9: API keys needed | B9: EIA (api.eia.gov), USPTO PatentsView, Senate LDA. All free, all instant, all email-verified. | C9: Register these BEFORE the clock starts. Three signup flows during a build is 30 minutes you do not have.
A10: Caching | B10: Cache every fetch and every extraction to disk as JSON keyed by ticker+field. Never re-fetch, never re-extract. | C10: You will rerun scoring 20+ times. Re-extraction is the single biggest avoidable time sink and the biggest avoidable cost.
A11: Schema freeze | B11: One repo, one schema.py, agreed before anyone generates extraction code. | C11: Four people generating four incompatible pipelines in parallel is the real hazard of moving fast. Costs 30 minutes, saves hours.
A12: Extraction record shape | B12: ticker, field, value, unit, quote, source_url, source_section, extracted_by, status | C12: status in {quote_verified, not_disclosed, quote_failed}. Every number carries a verbatim quote or it is null.
A13: Quote validation | B13: If quote is not a character-for-character substring of the source text, discard and mark not_disclosed. | C13: Mechanical, cheap, and catches most confident-but-wrong extractions. 'Not disclosed' is a signal, not a gap.
A14: Pre-filtering filings | B14: Strip HTML, locate section by heading, keep +/-2-3k chars around keyword hits. 5-15k tokens sent, not 200k. | C14: ~15x cheaper, faster, and MORE accurate — long context dilutes attention on the relevant passage.
A15: Manifest | B15: One row per company per field with status. Chart coverage by sector on your own dashboard. | C15: Silent partial failure is the failure mode you will not notice until the demo. The manifest makes it visible, and the coverage chart becomes a slide.
... A20: Verify before scoping | B20: Download the SBTi CSV and the GHGRP parent file, join both to your ticker list, count the matches. | C20: About two hours, and it tells you whether the transition pillar has enough data to stand up before you build it.
